README.md
setup.py
bin/vent
vent/__init__.py
vent/menu.py
vent.egg-info/PKG-INFO
vent.egg-info/SOURCES.txt
vent.egg-info/dependency_links.txt
vent.egg-info/requires.txt
vent.egg-info/top_level.txt
vent/api/__init__.py
vent/api/image.py
vent/api/repository.py
vent/api/system.py
vent/api/tools.py
vent/core/__init__.py
vent/core/file_drop/__init__.py
vent/core/file_drop/file_drop.py
vent/core/file_drop/test_file_drop.py
vent/core/rq_worker/__init__.py
vent/core/rq_worker/settings.py
vent/core/rq_worker/test_watch.py
vent/core/rq_worker/watch.py
vent/extras/network_tap/__init__.py
vent/extras/network_tap/ncontrol/__init__.py
vent/extras/network_tap/ncontrol/ncontrol.py
vent/extras/network_tap/ncontrol/paths.py
vent/extras/network_tap/ncontrol/routes.py
vent/extras/network_tap/ncontrol/test_ncontrol.py
vent/extras/rmq_es_connector/__init__.py
vent/extras/rmq_es_connector/rmq_es_connector.py
vent/extras/rmq_es_connector/test_rmq_es_connector.py
vent/extras/rq_dashboard/__init__.py
vent/extras/rq_dashboard/rq_dash_settings.py
vent/extras/rq_dashboard/test_rq_dashboard.py
vent/helpers/__init__.py
vent/helpers/errors.py
vent/helpers/logs.py
vent/helpers/meta.py
vent/helpers/paths.py
vent/helpers/templates.py
vent/menus/__init__.py
vent/menus/add.py
vent/menus/add_options.py
vent/menus/backup.py
vent/menus/choose_tools.py
vent/menus/del_instances.py
vent/menus/editor.py
vent/menus/help.py
vent/menus/inventory.py
vent/menus/inventory_forms.py
vent/menus/main.py
vent/menus/services.py
vent/menus/tools.py
vent/menus/tutorial_forms.py
vent/menus/tutorials.py