Metadata-Version: 1.2
Name: vent
Version: 0.10.1
Summary: A library that includes a CLI designed to serve as a platform to collect and analyze data across a flexible set of tools and technologies.
Home-page: https://github.com/CyberReboot/vent
Author: arpit
Author-email: 
Maintainer: Charlie Lewis
Maintainer-email: clewis@iqt.org
License: Apache License 2.0
Keywords: docker containers platform collection analysis tools devops
Platform: UNKNOWN
